quantastica_qiskit_forest-0.9.21-py3.10-nspkg.pth
quantastica/qiskit_forest/ForestBackend.py
quantastica/qiskit_forest/ForestJob.py
quantastica/qiskit_forest/__init__.py
tests/__init__.py
tests/test_forestbackend.py
tests/test_qaoa.py
quantastica_qiskit_forest-0.9.21.dist-info/LICENSE
quantastica_qiskit_forest-0.9.21.dist-info/METADATA
quantastica_qiskit_forest-0.9.21.dist-info/WHEEL
quantastica_qiskit_forest-0.9.21.dist-info/namespace_packages.txt
quantastica_qiskit_forest-0.9.21.dist-info/top_level.txt
quantastica_qiskit_forest-0.9.21.dist-info/RECORD
