Metadata-Version: 2.1
Name: quantastica-qiskit-forest
Version: 0.9.21
Summary: Forest backend for Qiskit: run Qiskit code on Rigetti quantum computers or simulators
Home-page: https://github.com/quantastica/qiskit-forest
Author: Quantastica
Author-email: support@quantastica.com
License: Apache License 2.0
Classifier: Development Status :: 4 - Beta
Classifier: License :: OSI Approved :: Apache Software License
Classifier: Programming Language :: Python :: 3
Classifier: Intended Audience :: Science/Research
License-File: LICENSE
Requires-Dist: qiskit
Requires-Dist: pyquil
Requires-Dist: numpy
Requires-Dist: quantastica-qconvert (>=0.9.18)
